{
  "formatVersion": 1,
  "database": {
    "version": 1,
    "identityHash": "bfc3d906f0bb8f2c5879982ddc5f13fe",
    "entities": [
      {
        "tableName": "favoriteRestaurant",
        "createSql": "CREATE TABLE IF NOT EXISTS `${TABLE_NAME}` (`id` TEXT NOT NULL, `name` TEXT NOT NULL, `shopPhoto` TEXT NOT NULL, `address` TEXT NOT NULL, `open` TEXT NOT NULL, `close` TEXT NOT NULL, `access` TEXT NOT NULL, `shopUrl` TEXT NOT NULL, `createdAt` INTEGER NOT NULL, `updatedAt` INTEGER NOT NULL, `lastViewedAt` INTEGER NOT NULL, PRIMARY KEY(`id`))",
        "fields": [
          {
            "fieldPath": "id",
            "columnName": "id",
            "affinity": "TEXT",
            "notNull": true
          },
          {
            "fieldPath": "name",
            "columnName": "name",
            "affinity": "TEXT",
            "notNull": true
          },
          {
            "fieldPath": "shopPhoto",
            "columnName": "shopPhoto",
            "affinity": "TEXT",
            "notNull": true
          },
          {
            "fieldPath": "address",
            "columnName": "address",
            "affinity": "TEXT",
            "notNull": true
          },
          {
            "fieldPath": "open",
            "columnName": "open",
            "affinity": "TEXT",
            "notNull": true
          },
          {
            "fieldPath": "close",
            "columnName": "close",
            "affinity": "TEXT",
            "notNull": true
          },
          {
            "fieldPath": "access",
            "columnName": "access",
            "affinity": "TEXT",
            "notNull": true
          },
          {
            "fieldPath": "shopUrl",
            "columnName": "shopUrl",
            "affinity": "TEXT",
            "notNull": true
          },
          {
            "fieldPath": "createdAt",
            "columnName": "createdAt",
            "affinity": "INTEGER",
            "notNull": true
          },
          {
            "fieldPath": "updatedAt",
            "columnName": "updatedAt",
            "affinity": "INTEGER",
            "notNull": true
          },
          {
            "fieldPath": "lastViewedAt",
            "columnName": "lastViewedAt",
            "affinity": "INTEGER",
            "notNull": true
          }
        ],
        "primaryKey": {
          "autoGenerate": false,
          "columnNames": [
            "id"
          ]
        },
        "indices": [],
        "foreignKeys": []
      }
    ],
    "views": [],
    "setupQueries": [
      "CREATE TABLE IF NOT EXISTS room_master_table (id INTEGER PRIMARY KEY,identity_hash TEXT)",
      "INSERT OR REPLACE INTO room_master_table (id,identity_hash) VALUES(42, 'bfc3d906f0bb8f2c5879982ddc5f13fe')"
    ]
  }
}